{
  "schema_version": "1.0",
  "standard": "KS B 1400",
  "sections": {
    "A": {
      "top_width_mm": 13,
      "height_mm": 8,
      "pitch_width_mm": 11,
      "min_pulley_dia_mm": 75,
      "standard_lengths_mm": [787, 813, 838, 864, 889, 914, 940, 965, 991, 1016,
                               1067, 1118, 1168, 1219, 1270, 1321, 1372, 1422, 1473,
                               1524, 1575, 1626, 1676, 1727, 1778, 1829, 1880, 1930,
                               1981, 2032, 2133, 2286, 2438, 2591, 2743]
    },
    "B": {
      "top_width_mm": 17,
      "height_mm": 11,
      "pitch_width_mm": 14,
      "min_pulley_dia_mm": 125,
      "standard_lengths_mm": [900, 965, 1016, 1067, 1118, 1168, 1219, 1270, 1321,
                               1372, 1422, 1473, 1524, 1575, 1626, 1676, 1727, 1778,
                               1829, 1880, 1930, 1981, 2032, 2133, 2235, 2337, 2438,
                               2540, 2642, 2743, 2845, 2946, 3048, 3150, 3251, 3353,
                               3454, 3556, 3658, 3759, 3861, 3962, 4064]
    },
    "C": {
      "top_width_mm": 22,
      "height_mm": 14,
      "pitch_width_mm": 19,
      "min_pulley_dia_mm": 200,
      "standard_lengths_mm": [1524, 1575, 1626, 1676, 1727, 1778, 1829, 1880, 1930,
                               1981, 2032, 2133, 2235, 2337, 2438, 2540, 2642, 2743,
                               2845, 2946, 3048, 3150, 3251, 3353, 3454, 3556, 3658,
                               3759, 3861, 3962, 4064, 4166, 4267, 4369, 4572, 4775,
                               4978, 5182, 5385, 5588, 5791, 5994, 6197, 6401]
    },
    "D": {
      "top_width_mm": 32,
      "height_mm": 19,
      "pitch_width_mm": 27,
      "min_pulley_dia_mm": 355,
      "standard_lengths_mm": [3048, 3150, 3251, 3353, 3454, 3556, 3658, 3759, 3861,
                               3962, 4064, 4166, 4267, 4369, 4572, 4775, 4978, 5182,
                               5385, 5588, 5791, 5994, 6197, 6401, 6604, 6807, 7010,
                               7214, 7417, 7620, 7925, 8230, 8534, 8839, 9144]
    }
  }
}
